LICENSE
README.md
setup.py
flowspot.egg-info/PKG-INFO
flowspot.egg-info/SOURCES.txt
flowspot.egg-info/dependency_links.txt
flowspot.egg-info/top_level.txt
models/__init__.py
models/model_base.py
models/ml/__init__.py
models/ml/appscanner/__init__.py
models/ml/appscanner/appscanner_main_model.py
models/ml/appscanner/eval.py
models/ml/appscanner/feature_extractor.py
models/ml/appscanner/hyper_params.py
models/ml/appscanner/min_max.py
models/ml/appscanner/model.py
models/ml/appscanner/train.py
models/ml/bind/__init__.py
models/ml/bind/bind_main_model.py
models/ml/bind/build_raw_dataset_from_graph.py
models/ml/bind/build_vector_dataset.py
models/ml/bind/eval.py
models/ml/bind/hyper_params.py
models/ml/bind/model.py
models/ml/bind/run.py
models/ml/bind/train.py
models/ml/cumul/__init__.py
models/ml/cumul/attack_cumul.py
models/ml/cumul/cumul_main_model.py
models/ml/cumul/feature_extractor.py
models/ml/cumul/hyper_params.py
models/ml/cumul/model.py
models/ml/cumul/model_predict.py
models/ml/cumul/model_train.py
models/ml/cumul/util.py