Metadata-Version: 2.1
Name: flowspot
Version: 1.1
Summary: A python lib to parse traffic flow information from pcaps
Home-page: https://github.com/jmhIcoding/traffic_classification_utils
Author: Minghao Jiang
Author-email: jiangminghao@iie.ac.cn
License: UNKNOWN
Platform: UNKNOWN
Classifier: Programming Language :: Python :: 3
Classifier: License :: OSI Approved :: MIT License
Classifier: Operating System :: OS Independent
License-File: LICENSE
